asc_cli/__init__.py
asc_cli/cli.py
asc_cli/api/__init__.py
asc_cli/api/auth.py
asc_cli/api/client.py
asc_cli/commands/__init__.py
asc_cli/commands/apps.py
asc_cli/commands/auth.py
asc_cli/commands/bulk.py
asc_cli/commands/subscriptions.py
asc_cli/commands/testflight.py
asc_cli/config/__init__.py
asc_cli/config/schema.py
asc_cli/models/__init__.py
asc_cli-0.2.1.dist-info/METADATA
asc_cli-0.2.1.dist-info/WHEEL
asc_cli-0.2.1.dist-info/entry_points.txt
asc_cli-0.2.1.dist-info/licenses/LICENSE
asc_cli-0.2.1.dist-info/RECORD
