Metadata-Version: 2.4
Name: asc-cli
Version: 0.2.1
Summary: A powerful CLI for Apple App Store Connect API
Project-URL: Homepage, https://github.com/yooz-labs/asc-cli
Project-URL: Documentation, https://github.com/yooz-labs/asc-cli#readme
Project-URL: Repository, https://github.com/yooz-labs/asc-cli
Project-URL: Issues, https://github.com/yooz-labs/asc-cli/issues
Author-email: Yooz Labs <hello@yooz.live>
License: BSD-3-Clause
License-File: LICENSE
Keywords: app-store-connect,apple,cli,subscriptions,testflight
Classifier: Development Status :: 3 - Alpha
Classifier: Environment :: Console
Classifier: Intended Audience :: Developers
Classifier: License :: OSI Approved :: BSD License
Classifier: Operating System :: OS Independent
Classifier: Programming Language :: Python :: 3
Classifier: Programming Language :: Python :: 3.10
Classifier: Programming Language :: Python :: 3.11
Classifier: Programming Language :: Python :: 3.12
Classifier: Programming Language :: Python :: 3.13
Classifier: Topic :: Software Development :: Build Tools
Classifier: Typing :: Typed
Requires-Python: >=3.10
Requires-Dist: httpx>=0.27.0
Requires-Dist: pydantic>=2.0.0
Requires-Dist: pyjwt[crypto]>=2.8.0
Requires-Dist: python-dotenv>=1.0.0
Requires-Dist: pyyaml>=6.0.0
Requires-Dist: rich>=13.0.0
Requires-Dist: typer>=0.12.0
Provides-Extra: dev
Requires-Dist: mypy>=1.10.0; extra == 'dev'
Requires-Dist: pre-commit>=3.7.0; extra == 'dev'
Requires-Dist: pytest-asyncio>=0.23.0; extra == 'dev'
Requires-Dist: pytest-cov>=4.0.0; extra == 'dev'
Requires-Dist: pytest-mock>=3.12.0; extra == 'dev'
Requires-Dist: pytest>=8.0.0; extra == 'dev'
Requires-Dist: respx>=0.21.0; extra == 'dev'
Requires-Dist: ruff>=0.5.0; extra == 'dev'
Requires-Dist: types-pyyaml>=6.0.0; extra == 'dev'
